rich_split/__init__.py
rich_split/exceptions.py
rich_split/cutters/__init__.py
rich_split/cutters/base_cutter.py
rich_split/cutters/markdown_cutter.py
rich_split/cutters/text_cutter.py
rich_split/joiners/__init__.py
rich_split/joiners/base_joiner.py
rich_split/joiners/markdown_joiner.py
rich_split/joiners/text_joiner.py
rich_split/splitters/__init__.py
rich_split/splitters/base_splitter.py
rich_split/splitters/markdown_splitter.py
rich_split/splitters/text_splitter.py
rich_split/utils/__init__.py
rich_split/utils/markdown.py
rich_split-0.1.2.dist-info/METADATA
rich_split-0.1.2.dist-info/WHEEL
rich_split-0.1.2.dist-info/licenses/LICENSE
rich_split-0.1.2.dist-info/RECORD
